Workbook
Name NativeTimeline_Date: #N/A
Name Slicer_Category: #N/A

Sheet Personal spending
A1: Date | B1: Month-year | C1: Unique Id | D1: Tran Type | E1: Payee | F1: Merchant | G1: Category | H1: Memo | I1: Amount | J1: Type
A2: 45660 | B2: =TEXT(A2,"yyyy-mm") -> 2025-01 | C2: 2025010301 | D2: EFTPOS | E2: NETFLIX.COMLOS GATOS CA | F2: Netflix | G2: =_xlfn.XLOOKUP(Export20251104132100[[#This Row],[Merchant]],Table3[Merchant],Table3[Category],"Unknown") -> Subscription | H2: EFTPOS | I2: -27.99 | J2: =IF(Export20251104132100[[#This Row],[Amount]]>=0,"In","out") -> out
A3: 45661 | B3: =TEXT(A3,"yyyy-mm") -> 2025-01 | C3: 2025010401 | D3: EFTPOS | E3: Spotify P32F135D5B Stockholm | F3: Spotify | G3: =_xlfn.XLOOKUP(Export20251104132100[[#This Row],[Merchant]],Table3[Merchant],Table3[Category],"Unknown") -> Subscription | H3: EFTPOS | I3: -8.99 | J3: =IF(Export20251104132100[[#This Row],[Amount]]>=0,"In","out") -> out | Q3: =AVERAGEIF(J:J,"Out",I:I) -> -33.518361
A4: 45662 | B4: =TEXT(A4,"yyyy-mm") -> 2025-01 | C4: 2025010501 | D4: EFTPOS | E4: Under ArmourManawa Bay Auckland | F4: Under Armour | G4: =_xlfn.XLOOKUP(Export20251104132100[[#This Row],[Merchant]],Table3[Merchant],Table3[Category],"Unknown") -> Shopping | H4: EFTPOS | I4: -35.52 | J4: =IF(Export20251104132100[[#This Row],[Amount]]>=0,"In","out") -> out
A5: 45662 | B5: =TEXT(A5,"yyyy-mm") -> 2025-01 | C5: 2025010502 | D5: EFTPOS | E5: YD AUCKLANDAIRPORT AUCKLAND | F5: YD Auckland | G5: =_xlfn.XLOOKUP(Export20251104132100[[#This Row],[Merchant]],Table3[Merchant],Table3[Category],"Unknown") -> Shopping | H5: EFTPOS | I5: -39.99 | J5: =IF(Export20251104132100[[#This Row],[Amount]]>=0,"In","out") -> out | R5: =SUMIF(I:I,J9,H:H) -> 0
A6: 45663 | B6: =TEXT(A6,"yyyy-mm") -> 2025-01 | C6: 2025010603 | D6: EFTPOS | E6: APPLE.COM/BILL SYDNEY | F6: Apple | G6: =_xlfn.XLOOKUP(Export20251104132100[[#This Row],[Merchant]],Table3[Merchant],Table3[Category],"Unknown") -> Entertainment | H6: EFTPOS | I6: -22.99 | J6: =IF(Export20251104132100[[#This Row],[Amount]]>=0,"In","out") -> out | Q6: =AVERAGEIF($J:$J, "In", $I:$I) -> 197.96944
A7: 45663 | B7: =TEXT(A7,"yyyy-mm") -> 2025-01 | C7: 2025010605 | D7: D/C | E7: D/C FROM STUDYLINK (MSD ) | F7: Studylink | G7: =_xlfn.XLOOKUP(Export20251104132100[[#This Row],[Merchant]],Table3[Merchant],Table3[Category],"Unknown") -> Income | H7: STUDALLOW | I7: 238.67 | J7: =IF(Export20251104132100[[#This Row],[Amount]]>=0,"In","out") -> In
A8: 45663 | B8: =TEXT(A8,"yyyy-mm") -> 2025-01 | C8: 2025010604 | D8: D/C | E8: D/C FROM STUDYLINK (MSD) | F8: Studylink | G8: =_xlfn.XLOOKUP(Export20251104132100[[#This Row],[Merchant]],Table3[Merchant],Table3[Category],"Unknown") -> Income | H8: LC PAYMENT | I8: 77.72 | J8: =IF(Export20251104132100[[#This Row],[Amount]]>=0,"In","out") -> In
A9: 45663 | B9: =TEXT(A9,"yyyy-mm") -> 2025-01 | C9: 2025010601 | D9: EFTPOS | E9: KOKODAK CHICKEN - UNATTE AUCKLAND | F9: Kokodak Chicken | G9: =_xlfn.XLOOKUP(Export20251104132100[[#This Row],[Merchant]],Table3[Merchant],Table3[Category],"Unknown") -> Food & dining | H9: EFTPOS | I9: -18.99 | J9: =IF(Export20251104132100[[#This Row],[Amount]]>=0,"In","out") -> out
A10: 45663 | B10: =TEXT(A10,"yyyy-mm") -> 2025-01 | C10: 2025010602 | D10: EFTPOS | E10: Lindt Sprungli AUCKLAND | F10: Lindt | G10: =_xlfn.XLOOKUP(Export20251104132100[[#This Row],[Merchant]],Table3[Merchant],Table3[Category],"Unknown") -> Food & dining | H10: EFTPOS | I10: -16 | J10: =IF(Export20251104132100[[#This Row],[Amount]]>=0,"In","out") -> out
A11: 45664 | B11: =TEXT(A11,"yyyy-mm") -> 2025-01 | C11: 2025010702 | D11: EFTPOS | E11: AT Hop Manukau Bus Manukau | F11: At Hop Manukau | G11: =_xlfn.XLOOKUP(Export20251104132100[[#This Row],[Merchant]],Table3[Merchant],Table3[Category],"Unknown") -> Transport | H11: EFTPOS | I11: -20 | J11: =IF(Export20251104132100[[#This Row],[Amount]]>=0,"In","out") -> out
A12: 45664 | B12: =TEXT(A12,"yyyy-mm") -> 2025-01 | C12: 2025010701 | D12: EFTPOS | E12: BIG BOSS BARBER CHAPEL R AUCKLAND | F12: Big boss | G12: =_xlfn.XLOOKUP(Export20251104132100[[#This Row],[Merchant]],Table3[Merchant],Table3[Category],"Unknown") -> Grooming | H12: EFTPOS | I12: -35.88 | J12: =IF(Export20251104132100[[#This Row],[Amount]]>=0,"In","out") -> out
A13: 45664 | B13: =TEXT(A13,"yyyy-mm") -> 2025-01 | C13: 2025010705 | D13: EFTPOS | E13: OffshoreServiceMargins | F13: OffshoreServiceMargins Ser | G13: =_xlfn.XLOOKUP(Export20251104132100[[#This Row],[Merchant]],Table3[Merchant],Table3[Category],"Unknown") -> Utilities | H13: EFTPOS | I13: -0.38 | J13: =IF(Export20251104132100[[#This Row],[Amount]]>=0,"In","out") -> out
A14: 45664 | B14: =TEXT(A14,"yyyy-mm") -> 2025-01 | C14: 2025010703 | D14: BILLPAY | E14: PMT TO FC12-3083-0791904-50 | F14: PMT To Fc12 | G14: =_xlfn.XLOOKUP(Export20251104132100[[#This Row],[Merchant]],Table3[Merchant],Table3[Category],"Unknown") -> Transfers | H14: BILL PAYMENT TO nv | I14: -15 | J14: =IF(Export20251104132100[[#This Row],[Amount]]>=0,"In","out") -> out
A15: 45664 | B15: =TEXT(A15,"yyyy-mm") -> 2025-01 | C15: 2025010704 | D15: EFTPOS | E15: Steam | F15: Steam | G15: =_xlfn.XLOOKUP(Export20251104132100[[#This Row],[Merchant]],Table3[Merchant],Table3[Category],"Unknown") -> Entertainment | H15: EFTPOS | I15: -17.89 | J15: =IF(Export20251104132100[[#This Row],[Amount]]>=0,"In","out") -> out
A16: 45665 | B16: =TEXT(A16,"yyyy-mm") -> 2025-01 | C16: 2025010802 | D16: EFTPOS | E16: CUE CITYAUCKLAND | F16: CUE City | G16: =_xlfn.XLOOKUP(Export20251104132100[[#This Row],[Merchant]],Table3[Merchant],Table3[Category],"Unknown") -> Entertainment | H16: EFTPOS | I16: -20.4 | J16: =IF(Export20251104132100[[#This Row],[Amount]]>=0,"In","out") -> out
A17: 45665 | B17: =TEXT(A17,"yyyy-mm") -> 2025-01 | C17: 2025010801 | D17: EFTPOS | E17: That Taco Place On Q Auckland | F17: The Taco Place | G17: =_xlfn.XLOOKUP(Export20251104132100[[#This Row],[Merchant]],Table3[Merchant],Table3[Category],"Unknown") -> Food & dining | H17: EFTPOS | I17: -14 | J17: =IF(Export20251104132100[[#This Row],[Amount]]>=0,"In","out") -> out
A18: 45666 | B18: =TEXT(A18,"yyyy-mm") -> 2025-01 | C18: 2025010904 | D18: EFTPOS | E18: AT Hop Auckland Auckland | F18: At Hop Manukau | G18: =_xlfn.XLOOKUP(Export20251104132100[[#This Row],[Merchant]],Table3[Merchant],Table3[Category],"Unknown") -> Transport | H18: EFTPOS | I18: -5 | J18: =IF(Export20251104132100[[#This Row],[Amount]]>=0,"In","out") -> out
... A220: 45963 | B220: =TEXT(A220,"yyyy-mm") -> 2025-11 | C220: 2025110201 | D220: D/C | E220: D/C FROM NZD 8.06 | F220: D/C From Nzd 8 | G220: =_xlfn.XLOOKUP(Export20251104132100[[#This Row],[Merchant]],Table3[Merchant],Table3[Category],"Unknown") -> Uncategorized | H220: AMAZON PRIME VIDEO NZ SINGAPORE | I220: 8.06 | J220: =IF(Export20251104132100[[#This Row],[Amount]]>=0,"In","out") -> In
I221: =SUBTOTAL(109, Export20251104132100[Amount]) -> 993.04

Sheet Category by month Year
A1: Month-year | B1: (All)
A3: Category | B3: Sum of Amount
A4: Education | B4: -74.14
A5: Entertainment | B5: -418.47
A6: Fees & Charges | B6: -10
A7: Fitness | B7: -79.95
A8: Food & dining | B8: -353.49
A9: Fuel | B9: -301.9
A10: Groceries | B10: -461.45
A11: Grooming | B11: -210.15
A12: Healthcare | B12: -59.67
A13: Income | B13: 7065.79
A14: Shopping | B14: -1239.42
A15: Subscription | B15: -377.27
... A19: Utilities | B19: -1691.8

Sheet MerchantMapping
A1: Merchant | B1: Category
A2: Netflix | B2: Subscription
A3: Spotify | B3: Subscription
A4: Under Armour | B4: Shopping
A5: YD Auckland | B5: Shopping
A6: Apple | B6: Entertainment
A7: Studylink | B7: Income
A8: Kokodak Chicken | B8: Food & dining
A9: Lindt | B9: Food & dining
A10: At Hop Manukau | B10: Transport
A11: Big boss | B11: Grooming
A12: OffshoreServiceMargins Ser | B12: Utilities
... A75: D/C From Nzd 8 | B75: Uncategorized

Sheet Pivot Tables
A1: Type | B1: (All) | F1: Spending by Merchant
A3: Row Labels | B3: Total Spent | C3: Transaction Count | D3: Spend % | F3: Row Labels | G3: Sum of Amount
A4: Education | B4: -74.14 | C4: 3 | D4: -0.074659631 | F4: Kokodak Chicken | G4: -18.99
A5: Entertainment | B5: -418.47 | C5: 20 | D5: -0.42140296 | F5: That Taco Place | G5: -12.85
A6: Fees & Charges | B6: -10 | C6: 1 | D6: -0.010070088 | F6: YD Auckland | G6: -39.99
A7: Fitness | B7: -79.95 | C7: 1 | D7: -0.080510352 | F7: 2DEGREES Mo | G7: -10
A8: Food & dining | B8: -353.49 | C8: 35 | D8: -0.35596753 | F8: Amazon | G8: -89.9
A9: Fuel | B9: -301.9 | C9: 12 | D9: -0.30401595 | F9: AMI Ami Insuran | G9: -1070.51
A10: Groceries | B10: -461.45 | C10: 13 | D10: -0.4646842 | F10: Apple | G10: -91.34
A11: Grooming | B11: -210.15 | C11: 5 | D11: -0.2116229 | F11: AT | G11: -2.8
A12: Healthcare | B12: -59.67 | C12: 3 | D12: -0.060088214 | F12: At Hop Manukau | G12: -75
A13: Income | B13: 7065.79 | C13: 37 | D13: 7.1153126 | F13: ATM Atm Deposit | G13: 1440
A14: Shopping | B14: -1239.42 | C14: 25 | D14: -1.2481068 | F14: AWANUI Manu | G14: -102
A15: Subscription | B15: -377.27 | C15: 23 | D15: -0.3799142 | F15: Beverley Hills | G15: -3.06
... A20: Grand Total | B20: 993.04 | C20: 219 | D20: 1 | F20: Chemist War | G20: -14.99
F21: Chemist Warehouse Nz | G21: -636.98
F22: Chemsit Warehouse Nz | G22: -16.99
F23: CUE City | G23: -20.4
F24: D c | G24: 2802
F25: D/C From | G25: 1193.35
F26: D/C From I.R.D | G26: 555.7
F27: D/C From Iag | G27: 104.36
F28: D/C From Nzd 8 | G28: 8.06
F29: D/C From Usd 1 | G29: 2.05
F30: DEBITSUCCESS Itsucces | G30: -51
F31: Dept Of Internal | G31: -470.2
F32: Event Cinemas Manukau | G32: -63.65
... F78: Grand Total | G78: 993.04

Sheet Income Sparklines
A1: Month-year | B1: income | C1: spending | D1: balance | E1: Income Sparkilne | F1: Spending Sparkline
A2: 2025-01 | B2: =SUMIFS('Personal spending'!I:I,'Personal spending'!J:J,"In",'Personal spending'!B:B,Table2[[#This Row],[Month-year]]) -> 1295.56 | C2: =-SUMIFS('Personal spending'!I:I,'Personal spending'!J:J,"out",'Personal spending'!B:B,Table2[[#This Row],[Month-year]]) -> 1442.3 | D2: =Table2[[#This Row],[income]]+Table2[[#This Row],[spending]] -> 2737.86
A3: 2025-02 | B3: =SUMIFS('Personal spending'!I:I,'Personal spending'!J:J,"In",'Personal spending'!B:B,Table2[[#This Row],[Month-year]]) -> 949.17 | C3: =-SUMIFS('Personal spending'!I:I,'Personal spending'!J:J,"out",'Personal spending'!B:B,Table2[[#This Row],[Month-year]]) -> 829.99 | D3: =Table2[[#This Row],[income]]+Table2[[#This Row],[spending]] -> 1779.16
A4: 2025-03 | B4: =SUMIFS('Personal spending'!I:I,'Personal spending'!J:J,"In",'Personal spending'!B:B,Table2[[#This Row],[Month-year]]) -> 130 | C4: =-SUMIFS('Personal spending'!I:I,'Personal spending'!J:J,"out",'Personal spending'!B:B,Table2[[#This Row],[Month-year]]) -> 361.35 | D4: =Table2[[#This Row],[income]]+Table2[[#This Row],[spending]] -> 491.35
A5: 2025-04 | B5: =SUMIFS('Personal spending'!I:I,'Personal spending'!J:J,"In",'Personal spending'!B:B,Table2[[#This Row],[Month-year]]) -> 430 | C5: =-SUMIFS('Personal spending'!I:I,'Personal spending'!J:J,"out",'Personal spending'!B:B,Table2[[#This Row],[Month-year]]) -> 398.45 | D5: =Table2[[#This Row],[income]]+Table2[[#This Row],[spending]] -> 828.45
A6: 2025-05 | B6: =SUMIFS('Personal spending'!I:I,'Personal spending'!J:J,"In",'Personal spending'!B:B,Table2[[#This Row],[Month-year]]) -> 150 | C6: =-SUMIFS('Personal spending'!I:I,'Personal spending'!J:J,"out",'Personal spending'!B:B,Table2[[#This Row],[Month-year]]) -> 260.36 | D6: =Table2[[#This Row],[income]]+Table2[[#This Row],[spending]] -> 410.36
A7: 2025-06 | B7: =SUMIFS('Personal spending'!I:I,'Personal spending'!J:J,"In",'Personal spending'!B:B,Table2[[#This Row],[Month-year]]) -> 685.7 | C7: =-SUMIFS('Personal spending'!I:I,'Personal spending'!J:J,"out",'Personal spending'!B:B,Table2[[#This Row],[Month-year]]) -> 522.13 | D7: =Table2[[#This Row],[income]]+Table2[[#This Row],[spending]] -> 1207.83
A8: 2025-07 | B8: =SUMIFS('Personal spending'!I:I,'Personal spending'!J:J,"In",'Personal spending'!B:B,Table2[[#This Row],[Month-year]]) -> 677.05 | C8: =-SUMIFS('Personal spending'!I:I,'Personal spending'!J:J,"out",'Personal spending'!B:B,Table2[[#This Row],[Month-year]]) -> 182.69 | D8: =Table2[[#This Row],[income]]+Table2[[#This Row],[spending]] -> 859.74
A9: 2025-08 | B9: =SUMIFS('Personal spending'!I:I,'Personal spending'!J:J,"In",'Personal spending'!B:B,Table2[[#This Row],[Month-year]]) -> 527.5 | C9: =-SUMIFS('Personal spending'!I:I,'Personal spending'!J:J,"out",'Personal spending'!B:B,Table2[[#This Row],[Month-year]]) -> 865.08 | D9: =Table2[[#This Row],[income]]+Table2[[#This Row],[spending]] -> 1392.58
A10: 2025-09 | B10: =SUMIFS('Personal spending'!I:I,'Personal spending'!J:J,"In",'Personal spending'!B:B,Table2[[#This Row],[Month-year]]) -> 1156.86 | C10: =-SUMIFS('Personal spending'!I:I,'Personal spending'!J:J,"out",'Personal spending'!B:B,Table2[[#This Row],[Month-year]]) -> 343.42 | D10: =Table2[[#This Row],[income]]+Table2[[#This Row],[spending]] -> 1500.28
A11: 2025-10 | B11: =SUMIFS('Personal spending'!I:I,'Personal spending'!J:J,"In",'Personal spending'!B:B,Table2[[#This Row],[Month-year]]) -> 1117 | C11: =-SUMIFS('Personal spending'!I:I,'Personal spending'!J:J,"out",'Personal spending'!B:B,Table2[[#This Row],[Month-year]]) -> 730.39 | D11: =Table2[[#This Row],[income]]+Table2[[#This Row],[spending]] -> 1847.39
A12: 2025-11 | B12: =SUMIFS('Personal spending'!I:I,'Personal spending'!J:J,"In",'Personal spending'!B:B,Table2[[#This Row],[Month-year]]) -> 8.06 | C12: =-SUMIFS('Personal spending'!I:I,'Personal spending'!J:J,"out",'Personal spending'!B:B,Table2[[#This Row],[Month-year]]) -> 197.7 | D12: =Table2[[#This Row],[income]]+Table2[[#This Row],[spending]] -> 205.76

Sheet Dashboard
A1: Personal Finance Dashboard
A3: Total Income | D3: Total Spending | G3: Net Balance
A4: =SUMIFS('Personal spending'!I:I,'Personal spending'!J:J,"In") -> 7126.9 | D4: =-SUMIFS('Personal spending'!I:I,'Personal spending'!J:J,"out") -> 6133.86 | G4: =A4-D4 -> 993.04
